gbox/__init__.py
gbox/base.py
gbox/lines.py
gbox/utils.py
gbox/gshape/__init__.py
gbox/gshape/ellipse.py
gbox/gshape/gshape.py
gbox-0.2.1.dist-info/licenses/LICENSE
gbox-0.2.1.dist-info/METADATA
gbox-0.2.1.dist-info/WHEEL
gbox-0.2.1.dist-info/top_level.txt
gbox-0.2.1.dist-info/RECORD
