Metadata-Version: 2.4
Name: gbox
Version: 0.2.1
Summary: A convenience package for geometry related operations
Author-email: Rajesh Nakka <338rajesh@gmail.com>
Maintainer-email: Rajesh Nakka <338rajesh@gmail.com>
License: MIT License
Project-URL: documentation, https://gbox.readthedocs.io
Project-URL: repository, https://github.com/338rajesh/gbox
Keywords: Geometry,Shapes,Plotting
Classifier: Programming Language :: Python :: 3
Classifier: License :: OSI Approved :: MIT License
Classifier: Operating System :: OS Independent
Requires-Python: >=3.11
License-File: LICENSE
Requires-Dist: numpy==2.2.0
Requires-Dist: matplotlib==3.10.0
Requires-Dist: scipy==1.15.2
Dynamic: license-file
